systock/__init__.py
systock/constants.py
systock/contexts.py
systock/exceptions.py
systock/logger.py
systock/models.py
systock/token_store.py
systock/utils.py
systock/brokers/__init__.py
systock/brokers/kis/__init__.py
systock/brokers/kis/auth.py
systock/brokers/kis/client.py
systock/brokers/kis/domestic.py
systock/brokers/kis/overseas.py
systock/brokers/kis/realtime.py
systock/interfaces/__init__.py
systock/interfaces/broker.py
sy_stock_api-0.0.1.dist-info/METADATA
sy_stock_api-0.0.1.dist-info/WHEEL
sy_stock_api-0.0.1.dist-info/top_level.txt
sy_stock_api-0.0.1.dist-info/RECORD
