Metadata-Version: 2.4
Name: sy-stock-api
Version: 0.0.1
Summary: Python interface for seamless integration with multiple Korean brokerage APIs
Author-email: Seungyeon Kim <ksy02k@gmail.com>
Project-URL: Homepage, https://github.com/Kimseonu0919/sy-stock-api
Requires-Python: >=3.9
Requires-Dist: requests>=2.28.0
Requires-Dist: python-dotenv>=1.0.0
Requires-Dist: websockets>=11.0
Provides-Extra: redis
Requires-Dist: redis>=4.0.0; extra == "redis"
Provides-Extra: secure
Requires-Dist: keyring>=24.0.0; extra == "secure"
Provides-Extra: dev
Requires-Dist: pytest>=7.0; extra == "dev"
Requires-Dist: black>=23.0; extra == "dev"
Requires-Dist: isort>=5.0; extra == "dev"
